[
  {
    "name": "CÔNG TY LUẬT PHÁP ĐỊNH",
    "category": "Legal services",
    "rating": 5,
    "reviewCount": 50,
    "address": "Address: 454 Nguyễn Thị Minh Khai, Bàn Cờ, Hồ Chí Minh 700000, Vietnam",
    "latitude": 10.7685565,
    "longitude": 106.6844793
  },
  {
    "name": "Trung Tâm Trợ Giúp Pháp Lý Nhà Nước số 1",
    "category": "Attorney",
    "rating": 4.4,
    "reviewCount": 44,
    "address": "Address: 470 Nguyễn Tri Phương, Vườn Lài, Hồ Chí Minh, Vietnam",
    "latitude": 10.7664943,
    "longitude": 106.6675516
  },
  {
    "name": "Dịch vụ làm lý lịch tư pháp",
    "category": "Justice department",
    "rating": 4.8,
    "reviewCount": 48,
    "address": "Address: 135 Đ. Số 12, Gò Vấp, Hồ Chí Minh, Vietnam",
    "latitude": null,
    "longitude": null
  },
  {
    "name": "HCMC Justice Department",
    "category": "Justice department",
    "rating": 2.4,
    "reviewCount": 24,
    "address": "Address: 143 Pasteur, Xuân Hòa, Hồ Chí Minh, Vietnam",
    "latitude": null,
    "longitude": null
  },
  {
    "name": "Tạp chí Pháp Lý",
    "category": "Corporate office",
    "rating": 5,
    "reviewCount": 50,
    "address": "Address: 208 Điện Biên Phủ, Xuân Hòa, Hồ Chí Minh, Vietnam",
    "latitude": 10.782981,
    "longitude": 106.6901063
  }
]